LICENSE
MANIFEST.in
README.md
setup.py
correcthorsebatterystaple/__init__.py
correcthorsebatterystaple/__main__.py
correcthorsebatterystaple/app.py
correcthorsebatterystaple.egg-info/PKG-INFO
correcthorsebatterystaple.egg-info/SOURCES.txt
correcthorsebatterystaple.egg-info/dependency_links.txt
correcthorsebatterystaple.egg-info/entry_points.txt
correcthorsebatterystaple.egg-info/requires.txt
correcthorsebatterystaple.egg-info/top_level.txt