Metadata-Version: 1.1
Name: correcthorsebatterystaple
Version: 0.1
Summary: Test application
Home-page: https://github.com/Frozenball/correcthorsebatterystaple
Author: Teemu Kokkonen
Author-email: teemu.on.ihminen@gmail.com
License: BSD
Keywords: example documentation tutorial
Platform: UNKNOWN
Classifier: Development Status :: 3 - Alpha
Classifier: Topic :: Utilities
Classifier: License :: OSI Approved :: BSD License
